configs/__init__.py
configs/parser.py
config_parser-0.0.1.dist-info/LICENSE
config_parser-0.0.1.dist-info/METADATA
config_parser-0.0.1.dist-info/WHEEL
config_parser-0.0.1.dist-info/top_level.txt
config_parser-0.0.1.dist-info/RECORD
