Metadata-Version: 2.1
Name: config_parser
Version: 0.0.1
Summary: Configuration library wrappers
Home-page: https://github.com/mattpaletta/configs
Author: Matthew Paletta
Author-email: mattpaletta@gmail.com
License: GNU GPLv3
Platform: UNKNOWN
Classifier: Development Status :: 3 - Alpha
Classifier: Intended Audience :: Developers
Classifier: License :: OSI Approved :: GNU Affero General Public License v3 or later (AGPLv3+)
Classifier: Operating System :: OS Independent
Classifier: Programming Language :: Python :: 3
Classifier: Topic :: Software Development :: Libraries
Classifier: Natural Language :: English
Requires-Python: >=3.6
